pymarkovclustering/__init__.py
pymarkovclustering/__main__.py
pymarkovclustering/logger.py
pymarkovclustering/main.py
pymarkovclustering/utils.py
pymarkovclustering/viz.py
pymarkovclustering/scripts/__init__.py
pymarkovclustering/scripts/pymcl.py
pymarkovclustering-0.1.1.dist-info/METADATA
pymarkovclustering-0.1.1.dist-info/WHEEL
pymarkovclustering-0.1.1.dist-info/entry_points.txt
pymarkovclustering-0.1.1.dist-info/licenses/LICENSE
pymarkovclustering-0.1.1.dist-info/RECORD
