Metadata-Version: 2.3
Name: pyMarkovClustering
Version: 0.1.1
Summary: Markov Clustering in Python
Author: moshi4
License: MIT
Keywords: bioinformatics,clustering,markov-clustering,network-graph
Classifier: Intended Audience :: Science/Research
Classifier: Topic :: Scientific/Engineering :: Bio-Informatics
Classifier: Topic :: Scientific/Engineering :: Information Analysis
Classifier: Topic :: Scientific/Engineering :: Mathematics
Requires-Python: >=3.9
Requires-Dist: numpy>=2.0.0
Requires-Dist: scikit-learn>=1.6.1
Requires-Dist: scipy>=1.10.1
